LICENSE
README.md
setup.py
mushmc_api/__init__.py
mushmc_api.egg-info/PKG-INFO
mushmc_api.egg-info/SOURCES.txt
mushmc_api.egg-info/dependency_links.txt
mushmc_api.egg-info/requires.txt
mushmc_api.egg-info/top_level.txt