Metadata-Version: 2.1
Name: mushmc-api
Version: 0.0.2
Summary: MushMC-API is a Python library for developers that facilitates access to the MushMC server API, making project creation more efficient and dynamic.
Home-page: https://github.com/Henrique-Coder/mushmc-api
Author: Henrique-Coder
Author-email: henriquemoreira10fk@gmail.com
Requires-Python: >=3.6
License-File: LICENSE
Requires-Dist: requests
